fwhassess/__init__.py
fwhassess/assesspv.py
fwhassess/utils.py
fwhassess/test/__init__.py
fwhassess/test/test_pv.json
fwhassess/test/test_pv.py
fwhassess-1.0.3.dist-info/LICENSE.txt
fwhassess-1.0.3.dist-info/METADATA
fwhassess-1.0.3.dist-info/WHEEL
fwhassess-1.0.3.dist-info/top_level.txt
fwhassess-1.0.3.dist-info/RECORD
