Metadata-Version: 2.2
Name: fwhassess
Version: 1.0.3
Summary: A standard code base for model performance evaluation.
Home-page: 
Author: lotuslaw
Author-email: Lotuslaw.Ni@franklinwh.com
License: MIT License
Platform: all
Classifier: Intended Audience :: Developers
Classifier: Operating System :: OS Independent
Classifier: Natural Language :: English
Classifier: Programming Language :: Python
Classifier: Programming Language :: Python :: 3.10
Classifier: Topic :: Software Development :: Libraries
License-File: LICENSE.txt
Requires-Dist: scikit-learn
Requires-Dist: pandas
Requires-Dist: numpy
Requires-Dist: matplotlib
Dynamic: author
Dynamic: author-email
Dynamic: classifier
Dynamic: description
Dynamic: license
Dynamic: platform
Dynamic: requires-dist
Dynamic: summary
